migrate_redmine_to_gitlab
