Metadata-Version: 1.1
Name: migrate-redmine-to-gitlab
Version: 2.0.2
Summary: Migrate a redmine project to Gitlab
Home-page: https://github/ultreia-io/migrate-redmine-to-gitlab
Author: Tony Chemit
Author-email: dev@tchemit.fr
License: GPL
Platform: UNKNOWN
Classifier: License :: OSI Approved :: GNU General Public License v3 (GPLv3)
